[{"content": {"chunk": "L\u00e4\u00e4ne prefektuuris kordonid puuduvad. Riigipiiri valvamise, piirikontrolli ja merep\u00e4\u00e4stega tegelevad maakondade politseijaoskondades asuvad merep\u00e4\u00e4stegrupid ning Schengeni kompensatsioonimeetmete patrullid.\nH\u00e4tta sattudes helista h\u00e4daabinumbrile 112.\nK\u00fcsimuste korral saab abi riigiinfo telefonilt 1247.", "imgurl": "", "title": "Kordonid - Politsei- ja Piirivalveamet", "description": "\nKordonid ja teenistuskohad. Asukoht. Korrapidaja. E-post. Narva. 3331580. Varnja. 3331690. Mehikoorma. 7861790. Saatse. 7861770. Piusa. 7861760. Luhamaa. 7861850. Mustvee. 3331670. V\u00e4rska. 7861780. L\u00e4\u00e4ne prefektuuris kordonid puuduvad. Riigipiiri valvamise, piirikontrolli ja merep\u00e4\u00e4stega tegelevad maakondade politseijaoskondades asuvad merep\u00e4\u00e4steg...", "source_url": "https://www.politsei.ee/et/kordonid"}}]