[{"content": {"chunk": "\u00dclekanne v\u00e4lisriigi pangast\nRiigil\u00f5ivu makse selgituses m\u00e4rgi taotletud dokumendi nimi, viitenumber ning inimese nimi, isikukood v\u00f5i s\u00fcnniaeg, kelle eest riigil\u00f5iv tasuti.\nRiigil\u00f5ivu saaja on rahandusministeerium.\n\n2900082443 - isikut t\u00f5endavad dokumendid, Eesti kodakondsus, elamisload, elamis\u00f5igused, l\u00fchiajaline t\u00f6\u00f6tamine ning viibimisaja pikendamine\n2900082469 - viisataotluse l\u00e4bivaatamine, t\u00e4htajalise elamisloa kehtivusaja l\u00f5ppemisest tuleneva Eestis viibimise \u00f5iguse pikaajalise viisana vormistamine ning viisa andmisest keeldumise, viisa t\u00fchistamise, viisa kehtetuks tunnistamise, viibimisaja pikendamisest keeldumise ja viibimisaja ennet\u00e4htaegse l\u00f5petamise otsuse vaidlustamise k\u00e4igus tehtud otsuse peale esitatud avalduse esmakordne l\u00e4bivaatamine.\n2900082456 - relvaseaduse alusel teostatavad toimingud\n2900082472 - riiklike tegevuslitsentside ja tegevuslubade v\u00e4ljastamine\n2900082498 - rahapesu andmeb\u00fcroo poolt tegevuslubade v\u00e4ljastamine\n\nMakstes riigil\u00f5ivu v\u00e4lispangast, on lisaks vaja teada ka Eestis asuva panga BIC ehk SWIFT koodi. Laekumine v\u00f5ib aega v\u00f5tta kuni 2 n\u00e4dalat.\n\n\n\nRohkem infot rahvusvaheliste \u00fclekannete kohta leiad enda panga kodulehelt.", "imgurl": "", "title": "\u00dclekanne v\u00e4lisriigi pangast - Kuidas riigil\u00f5ivu maksta? - Politsei- ja Piirivalveamet", "description": "V\u00e4lispangast riigil\u00f5ivu tasumine. Riigil\u00f5ivu makse selgituses m\u00e4rgi taotletud dokumendi nimi, viitenumber ning inimese nimi, isikukood v\u00f5i s\u00fcnniaeg, kelle eest riigil\u00f5iv tasuti. Riigil\u00f5ivu saaja on rahandusministeerium. Viitenumbrid. 2900082443 - isikut t\u00f5endavad dokumendid, Eesti kodakondsus, elamisload, elamis\u00f5igused, l\u00fchiajaline t\u00f6\u00f6tamine ning v...", "source_url": "https://www.politsei.ee/et/juhend/riigiloivud/ulekanne-valisriigi-pangast"}}]